<WELayout>
  <self itemName="Digital 3L Info Sign">
    <transform alignment="Left" isAbsoluteScale="true" arrayAxisOrder="XYZ">
      <offsetPosition x="0.6700001" y="6.27" z="0.36" />
      <offsetRotation x="-0" y="0" z="0" />
      <scale x="9" y="2.25" z="1" />
      <mustDraw>1</mustDraw>
      <instanceCount>-1</instanceCount>
      <arrayInstances x="1" y="1" z="1" />
      <arraySpacing x="0" y="0" z="0" />
    </transform>
    <imageMesh atlas="MaestroGermanSigns:Ger White Localroad">
      <mesh></mesh>
      <image>Local Empty Wide</image>
    </imageMesh>
    <defaultStyle>
      <color>FFFFFFFF</color>
      <emissiveColor>FFFFFFFF</emissiveColor>
      <metallic>0</metallic>
      <smoothness>0</smoothness>
      <emissiveIntensity>0</emissiveIntensity>
      <emissiveExposureWeight>0</emissiveExposureWeight>
      <coatStrength>0</coatStrength>
      <colorMask1>FFFFFF</colorMask1>
      <colorMask2>FFFFFF</colorMask2>
      <colorMask3>FFFFFF</colorMask3>
    </defaultStyle>
  </self>
  <children>
    <self itemName="Left Digital Icon Panel">
      <transform alignment="Left" arrayAxisOrder="XYZ">
        <offsetPosition x="1.88999987" y="0.350000024" z="0" />
        <offsetRotation x="-0" y="0" z="0" />
        <scale x="1.25" y="1.25" z="1" />
        <mustDraw>1</mustDraw>
        <instanceCount>-1</instanceCount>
        <arrayInstances x="1" y="1" z="1" />
        <arraySpacing x="0" y="0" z="0" />
      </transform>
      <imageMesh atlas="MaestroGermanSigns:Ger Blue Autobahn">
        <mesh></mesh>
        <image>Digital Info Frame + Icon</image>
      </imageMesh>
      <defaultStyle>
        <color>FFFFFFFF</color>
        <emissiveColor>FFFFFFFF</emissiveColor>
        <metallic>0</metallic>
        <smoothness>0</smoothness>
        <emissiveIntensity>4.623413</emissiveIntensity>
        <emissiveExposureWeight>0</emissiveExposureWeight>
        <coatStrength>0</coatStrength>
        <colorMask1>FFFFFF</colorMask1>
        <colorMask2>FFFFFF</colorMask2>
        <colorMask3>FFFFFF</colorMask3>
      </defaultStyle>
    </self>
    <children>
      <self itemName="Digital Image">
        <transform alignment="Left" arrayAxisOrder="XYZ">
          <offsetPosition x="1.01" y="0.18" z="0" />
          <offsetRotation x="-0" y="0" z="0" />
          <scale x="0.65" y="0.65" z="1" />
          <mustDraw>1</mustDraw>
          <instanceCount>-1</instanceCount>
          <arrayInstances x="1" y="1" z="1" />
          <arraySpacing x="0" y="0" z="0" />
        </transform>
        <imageMesh atlas="MaestroGermanSigns:Ger Blue Autobahn">
          <mesh></mesh>
          <image>Digital Trafficjam</image>
        </imageMesh>
        <defaultStyle>
          <color>FFFFFFFF</color>
          <emissiveColor>FFFFFFFF</emissiveColor>
          <metallic>0</metallic>
          <smoothness>0</smoothness>
          <emissiveIntensity>9</emissiveIntensity>
          <emissiveExposureWeight>0</emissiveExposureWeight>
          <coatStrength>0</coatStrength>
          <colorMask1>FFFFFF</colorMask1>
          <colorMask2>FFFFFF</colorMask2>
          <colorMask3>FFFFFF</colorMask3>
        </defaultStyle>
      </self>
      <children>
        <self itemName="Extra Line">
          <transform alignment="Left" arrayAxisOrder="XYZ">
            <offsetPosition x="0" y="-0.625" z="0" />
            <offsetRotation x="-0" y="0" z="0" />
            <scale x="0.15" y="0.15" z="1" />
            <mustDraw>1</mustDraw>
            <instanceCount>-1</instanceCount>
            <arrayInstances x="1" y="1" z="1" />
            <arraySpacing x="0" y="0" z="0" />
          </transform>
          <textMesh fontName="din1451alt">
            <text>STAU</text>
            <MaxWidthMeters>0</MaxWidthMeters>
          </textMesh>
          <defaultStyle>
            <color>FFFFFFFF</color>
            <emissiveColor>FFFFFFFF</emissiveColor>
            <metallic>0</metallic>
            <smoothness>0</smoothness>
            <emissiveIntensity>1.23872113</emissiveIntensity>
            <emissiveExposureWeight>0</emissiveExposureWeight>
            <coatStrength>0</coatStrength>
            <colorMask1>FFFFFF</colorMask1>
            <colorMask2>FFFFFF</colorMask2>
            <colorMask3>FFFFFF</colorMask3>
          </defaultStyle>
        </self>
      </children>
    </children>
    <children>
      <self itemName="---1st Line---">
        <transform alignment="Left" arrayAxisOrder="XYZ">
          <offsetPosition x="0.0899999961" y="0.38" z="0" />
          <offsetRotation x="-0" y="0" z="0" />
          <scale x="0.15" y="0.15" z="1" />
          <mustDraw>1</mustDraw>
          <instanceCount>-1</instanceCount>
          <arrayInstances x="1" y="1" z="1" />
          <arraySpacing x="0" y="0" z="0" />
        </transform>
        <textMesh fontName="din1451alt">
          <text>Baustelle</text>
          <MaxWidthMeters>0</MaxWidthMeters>
        </textMesh>
        <defaultStyle>
          <color>FFFFFFFF</color>
          <emissiveColor>FFFFFFFF</emissiveColor>
          <metallic>0</metallic>
          <smoothness>0</smoothness>
          <emissiveIntensity>1.23872113</emissiveIntensity>
          <emissiveExposureWeight>0</emissiveExposureWeight>
          <coatStrength>0</coatStrength>
          <colorMask1>FFFFFF</colorMask1>
          <colorMask2>FFFFFF</colorMask2>
          <colorMask3>FFFFFF</colorMask3>
        </defaultStyle>
      </self>
      <children>
        <self itemName="Digital Numberplate">
          <transform alignment="Left" arrayAxisOrder="XYZ">
            <offsetPosition x="-0.74" y="0" z="0" />
            <offsetRotation x="-0" y="0" z="0" />
            <scale x="0.225" y="0.225" z="1" />
            <mustDraw>1</mustDraw>
            <instanceCount>-1</instanceCount>
            <arrayInstances x="1" y="1" z="1" />
            <arraySpacing x="0" y="0" z="0" />
          </transform>
          <imageMesh atlas="MaestroGermanSigns:Ger Blue Autobahn">
            <mesh></mesh>
            <image>Digital Autobahn Number</image>
          </imageMesh>
          <defaultStyle>
            <color>FFFFFFFF</color>
            <emissiveColor>FFFFFFFF</emissiveColor>
            <metallic>0</metallic>
            <smoothness>0</smoothness>
            <emissiveIntensity>1.23872113</emissiveIntensity>
            <emissiveExposureWeight>0</emissiveExposureWeight>
            <coatStrength>0</coatStrength>
            <colorMask1>FFFFFF</colorMask1>
            <colorMask2>FFFFFF</colorMask2>
            <colorMask3>FFFFFF</colorMask3>
          </defaultStyle>
        </self>
        <children>
          <self itemName="Digital Number">
            <transform alignment="Left" arrayAxisOrder="XYZ">
              <offsetPosition x="0" y="0" z="0" />
              <offsetRotation x="-0" y="0" z="0" />
              <scale x="0.15" y="0.15" z="1" />
              <mustDraw>1</mustDraw>
              <instanceCount>-1</instanceCount>
              <arrayInstances x="1" y="1" z="1" />
              <arraySpacing x="0" y="0" z="0" />
            </transform>
            <textMesh fontName="DINMittelschriftStd">
              <text>1</text>
              <MaxWidthMeters>0</MaxWidthMeters>
            </textMesh>
            <defaultStyle>
              <color>FFFFFFFF</color>
              <emissiveColor>FFFFFFFF</emissiveColor>
              <metallic>0</metallic>
              <smoothness>0</smoothness>
              <emissiveIntensity>1.23872113</emissiveIntensity>
              <emissiveExposureWeight>0</emissiveExposureWeight>
              <coatStrength>0</coatStrength>
              <colorMask1>FFFFFF</colorMask1>
              <colorMask2>FFFFFF</colorMask2>
              <colorMask3>FFFFFF</colorMask3>
            </defaultStyle>
          </self>
        </children>
      </children>
    </children>
    <children>
      <self itemName="---2nd Line---">
        <transform alignment="Left" arrayAxisOrder="XYZ">
          <offsetPosition x="0.23999998" y="-9.313226E-09" z="0" />
          <offsetRotation x="-0" y="0" z="0" />
          <scale x="0.15" y="0.15" z="1" />
          <mustDraw>1</mustDraw>
          <instanceCount>-1</instanceCount>
          <arrayInstances x="1" y="1" z="1" />
          <arraySpacing x="0" y="0" z="0" />
        </transform>
        <textMesh fontName="din1451alt">
          <text>hinter</text>
          <MaxWidthMeters>0</MaxWidthMeters>
        </textMesh>
        <defaultStyle>
          <color>FFFFFFFF</color>
          <emissiveColor>FFFFFFFF</emissiveColor>
          <metallic>0</metallic>
          <smoothness>0</smoothness>
          <emissiveIntensity>1.23872113</emissiveIntensity>
          <emissiveExposureWeight>0</emissiveExposureWeight>
          <coatStrength>0</coatStrength>
          <colorMask1>FFFFFF</colorMask1>
          <colorMask2>FFFFFF</colorMask2>
          <colorMask3>FFFFFF</colorMask3>
        </defaultStyle>
      </self>
    </children>
    <children>
      <self itemName="---3rd Line---">
        <transform alignment="Left" arrayAxisOrder="XYZ">
          <offsetPosition x="-0.230000019" y="-0.37" z="0" />
          <offsetRotation x="-0" y="0" z="0" />
          <scale x="0.15" y="0.15" z="1" />
          <mustDraw>1</mustDraw>
          <instanceCount>-1</instanceCount>
          <arrayInstances x="1" y="1" z="1" />
          <arraySpacing x="0" y="0" z="0" />
        </transform>
        <textMesh fontName="din1451alt">
          <text>Kreuz Köln-West</text>
          <MaxWidthMeters>0</MaxWidthMeters>
        </textMesh>
        <defaultStyle>
          <color>FFFFFFFF</color>
          <emissiveColor>FFFFFFFF</emissiveColor>
          <metallic>0</metallic>
          <smoothness>0</smoothness>
          <emissiveIntensity>1.23872113</emissiveIntensity>
          <emissiveExposureWeight>0</emissiveExposureWeight>
          <coatStrength>0</coatStrength>
          <colorMask1>FFFFFF</colorMask1>
          <colorMask2>FFFFFF</colorMask2>
          <colorMask3>FFFFFF</colorMask3>
        </defaultStyle>
      </self>
    </children>
  </children>
  <children>
    <self itemName="Right Digital Panel">
      <transform alignment="Left" arrayAxisOrder="XYZ">
        <offsetPosition x="-2.72999978" y="0.350000024" z="0" />
        <offsetRotation x="-0" y="0" z="0" />
        <scale x="1.25" y="1.25" z="1" />
        <mustDraw>1</mustDraw>
        <instanceCount>-1</instanceCount>
        <arrayInstances x="1" y="1" z="1" />
        <arraySpacing x="0" y="0" z="0" />
      </transform>
      <imageMesh atlas="MaestroGermanSigns:Ger Blue Autobahn">
        <mesh></mesh>
        <image>Digital Info Frame</image>
      </imageMesh>
      <defaultStyle>
        <color>FFFFFFFF</color>
        <emissiveColor>FFFFFFFF</emissiveColor>
        <metallic>0</metallic>
        <smoothness>0</smoothness>
        <emissiveIntensity>4.623413</emissiveIntensity>
        <emissiveExposureWeight>0</emissiveExposureWeight>
        <coatStrength>0</coatStrength>
        <colorMask1>FFFFFF</colorMask1>
        <colorMask2>FFFFFF</colorMask2>
        <colorMask3>FFFFFF</colorMask3>
      </defaultStyle>
    </self>
    <children>
      <self itemName="---1st Line---">
        <transform alignment="Left" arrayAxisOrder="XYZ">
          <offsetPosition x="1.02" y="0.38" z="0" />
          <offsetRotation x="-0" y="0" z="0" />
          <scale x="0.15" y="0.15" z="1" />
          <mustDraw>1</mustDraw>
          <instanceCount>-1</instanceCount>
          <arrayInstances x="1" y="1" z="1" />
          <arraySpacing x="0" y="0" z="0" />
        </transform>
        <textMesh fontName="din1451alt">
          <text>Lövenich</text>
          <MaxWidthMeters>0</MaxWidthMeters>
        </textMesh>
        <defaultStyle>
          <color>FFFFFFFF</color>
          <emissiveColor>FFFFFFFF</emissiveColor>
          <metallic>0</metallic>
          <smoothness>0</smoothness>
          <emissiveIntensity>1.23872113</emissiveIntensity>
          <emissiveExposureWeight>0</emissiveExposureWeight>
          <coatStrength>0</coatStrength>
          <colorMask1>FFFFFF</colorMask1>
          <colorMask2>FFFFFF</colorMask2>
          <colorMask3>FFFFFF</colorMask3>
        </defaultStyle>
      </self>
    </children>
    <children>
      <self itemName="---2nd Line---">
        <transform alignment="Left" arrayAxisOrder="XYZ">
          <offsetPosition x="0.63" y="-9.313226E-09" z="0" />
          <offsetRotation x="-0" y="0" z="0" />
          <scale x="0.15" y="0.15" z="1" />
          <mustDraw>1</mustDraw>
          <instanceCount>-1</instanceCount>
          <arrayInstances x="1" y="1" z="1" />
          <arraySpacing x="0" y="0" z="0" />
        </transform>
        <textMesh fontName="din1451alt">
          <text>Köln-Zentrum via</text>
          <MaxWidthMeters>0</MaxWidthMeters>
        </textMesh>
        <defaultStyle>
          <color>FFFFFFFF</color>
          <emissiveColor>FFFFFFFF</emissiveColor>
          <metallic>0</metallic>
          <smoothness>0</smoothness>
          <emissiveIntensity>1.23872113</emissiveIntensity>
          <emissiveExposureWeight>0</emissiveExposureWeight>
          <coatStrength>0</coatStrength>
          <colorMask1>FFFFFF</colorMask1>
          <colorMask2>FFFFFF</colorMask2>
          <colorMask3>FFFFFF</colorMask3>
        </defaultStyle>
      </self>
    </children>
    <children>
      <self itemName="---3rd Line---">
        <transform alignment="Left" arrayAxisOrder="XYZ">
          <offsetPosition x="0.279999971" y="-0.37" z="0" />
          <offsetRotation x="-0" y="0" z="0" />
          <scale x="0.15" y="0.15" z="1" />
          <mustDraw>1</mustDraw>
          <instanceCount>-1</instanceCount>
          <arrayInstances x="1" y="1" z="1" />
          <arraySpacing x="0" y="0" z="0" />
        </transform>
        <textMesh fontName="din1451alt">
          <text>Frenchen-Nord</text>
          <MaxWidthMeters>0</MaxWidthMeters>
        </textMesh>
        <defaultStyle>
          <color>FFFFFFFF</color>
          <emissiveColor>FFFFFFFF</emissiveColor>
          <metallic>0</metallic>
          <smoothness>0</smoothness>
          <emissiveIntensity>1.23872113</emissiveIntensity>
          <emissiveExposureWeight>0</emissiveExposureWeight>
          <coatStrength>0</coatStrength>
          <colorMask1>FFFFFF</colorMask1>
          <colorMask2>FFFFFF</colorMask2>
          <colorMask3>FFFFFF</colorMask3>
        </defaultStyle>
      </self>
      <children>
        <self itemName="Junction Plate">
          <transform alignment="Left" arrayAxisOrder="XYZ">
            <offsetPosition x="0.96" y="0" z="0" />
            <offsetRotation x="-0" y="0" z="0" />
            <scale x="0.2" y="0.2" z="1" />
            <mustDraw>1</mustDraw>
            <instanceCount>-1</instanceCount>
            <arrayInstances x="1" y="1" z="1" />
            <arraySpacing x="0" y="0" z="0" />
          </transform>
          <imageMesh atlas="MaestroGermanSigns:Ger Blue Autobahn">
            <mesh></mesh>
            <image>Digital Junction Long</image>
          </imageMesh>
          <defaultStyle>
            <color>FFFFFFFF</color>
            <emissiveColor>FFFFFFFF</emissiveColor>
            <metallic>0</metallic>
            <smoothness>0</smoothness>
            <emissiveIntensity>1.23872113</emissiveIntensity>
            <emissiveExposureWeight>0</emissiveExposureWeight>
            <coatStrength>0</coatStrength>
            <colorMask1>FFFFFF</colorMask1>
            <colorMask2>FFFFFF</colorMask2>
            <colorMask3>FFFFFF</colorMask3>
          </defaultStyle>
        </self>
        <children>
          <self itemName="Junction Number">
            <transform alignment="Left" arrayAxisOrder="XYZ">
              <offsetPosition x="0" y="0" z="0" />
              <offsetRotation x="-0" y="0" z="0" />
              <scale x="0.125" y="0.125" z="1" />
              <mustDraw>1</mustDraw>
              <instanceCount>-1</instanceCount>
              <arrayInstances x="1" y="1" z="1" />
              <arraySpacing x="0" y="0" z="0" />
            </transform>
            <textMesh fontName="DINMittelschriftStd">
              <text>9b</text>
              <MaxWidthMeters>0</MaxWidthMeters>
            </textMesh>
            <defaultStyle>
              <color>FFFFFFFF</color>
              <emissiveColor>FFFFFFFF</emissiveColor>
              <metallic>0</metallic>
              <smoothness>0</smoothness>
              <emissiveIntensity>1.23872113</emissiveIntensity>
              <emissiveExposureWeight>0</emissiveExposureWeight>
              <coatStrength>0</coatStrength>
              <colorMask1>FFFFFF</colorMask1>
              <colorMask2>FFFFFF</colorMask2>
              <colorMask3>FFFFFF</colorMask3>
            </defaultStyle>
          </self>
        </children>
      </children>
    </children>
  </children>
  <children>
    <self itemName="AutobahnPlate L">
      <transform alignment="Left" arrayAxisOrder="XYZ">
        <offsetPosition x="3" y="-0.8" z="0" />
        <offsetRotation x="-0" y="0" z="0" />
        <scale x="0.3" y="0.3" z="1" />
        <mustDraw>1</mustDraw>
        <instanceCount>-1</instanceCount>
        <arrayInstances x="1" y="1" z="1" />
        <arraySpacing x="0" y="0" z="0" />
      </transform>
      <imageMesh atlas="MaestroGermanSigns:Ger Blue Autobahn">
        <mesh></mesh>
        <image>Autobahn Number</image>
      </imageMesh>
      <defaultStyle>
        <color>FFFFFFFF</color>
        <emissiveColor>FFFFFFFF</emissiveColor>
        <metallic>0</metallic>
        <smoothness>0</smoothness>
        <emissiveIntensity>0</emissiveIntensity>
        <emissiveExposureWeight>0</emissiveExposureWeight>
        <coatStrength>0</coatStrength>
        <colorMask1>FFFFFF</colorMask1>
        <colorMask2>FFFFFF</colorMask2>
        <colorMask3>FFFFFF</colorMask3>
      </defaultStyle>
    </self>
    <children>
      <self itemName="Number">
        <transform alignment="Left" arrayAxisOrder="XYZ">
          <offsetPosition x="0" y="0" z="0" />
          <offsetRotation x="-0" y="0" z="0" />
          <scale x="0.2" y="0.2" z="1" />
          <mustDraw>1</mustDraw>
          <instanceCount>-1</instanceCount>
          <arrayInstances x="1" y="1" z="1" />
          <arraySpacing x="0" y="0" z="0" />
        </transform>
        <textMesh fontName="DINMittelschriftStd">
          <text>4</text>
          <MaxWidthMeters>0</MaxWidthMeters>
        </textMesh>
        <defaultStyle>
          <color>FFFFFFFF</color>
          <emissiveColor>FFFFFFFF</emissiveColor>
          <metallic>0</metallic>
          <smoothness>0</smoothness>
          <emissiveIntensity>0</emissiveIntensity>
          <emissiveExposureWeight>0</emissiveExposureWeight>
          <coatStrength>0</coatStrength>
          <colorMask1>FFFFFF</colorMask1>
          <colorMask2>FFFFFF</colorMask2>
          <colorMask3>FFFFFF</colorMask3>
        </defaultStyle>
      </self>
    </children>
  </children>
  <children>
    <self itemName="AutobahnPlate R">
      <transform alignment="Left" arrayAxisOrder="XYZ">
        <offsetPosition x="0.65" y="-0.8" z="0" />
        <offsetRotation x="-0" y="0" z="0" />
        <scale x="0.3" y="0.3" z="1" />
        <mustDraw>1</mustDraw>
        <instanceCount>-1</instanceCount>
        <arrayInstances x="1" y="1" z="1" />
        <arraySpacing x="0" y="0" z="0" />
      </transform>
      <imageMesh atlas="MaestroGermanSigns:Ger Blue Autobahn">
        <mesh></mesh>
        <image>Autobahn Number</image>
      </imageMesh>
      <defaultStyle>
        <color>FFFFFFFF</color>
        <emissiveColor>FFFFFFFF</emissiveColor>
        <metallic>0</metallic>
        <smoothness>0</smoothness>
        <emissiveIntensity>0</emissiveIntensity>
        <emissiveExposureWeight>0</emissiveExposureWeight>
        <coatStrength>0</coatStrength>
        <colorMask1>FFFFFF</colorMask1>
        <colorMask2>FFFFFF</colorMask2>
        <colorMask3>FFFFFF</colorMask3>
      </defaultStyle>
    </self>
    <children>
      <self itemName="Number">
        <transform alignment="Left" arrayAxisOrder="XYZ">
          <offsetPosition x="0" y="0" z="0" />
          <offsetRotation x="-0" y="0" z="0" />
          <scale x="0.2" y="0.2" z="1" />
          <mustDraw>1</mustDraw>
          <instanceCount>-1</instanceCount>
          <arrayInstances x="1" y="1" z="1" />
          <arraySpacing x="0" y="0" z="0" />
        </transform>
        <textMesh fontName="DINMittelschriftStd">
          <text>4</text>
          <MaxWidthMeters>0</MaxWidthMeters>
        </textMesh>
        <defaultStyle>
          <color>FFFFFFFF</color>
          <emissiveColor>FFFFFFFF</emissiveColor>
          <metallic>0</metallic>
          <smoothness>0</smoothness>
          <emissiveIntensity>0</emissiveIntensity>
          <emissiveExposureWeight>0</emissiveExposureWeight>
          <coatStrength>0</coatStrength>
          <colorMask1>FFFFFF</colorMask1>
          <colorMask2>FFFFFF</colorMask2>
          <colorMask3>FFFFFF</colorMask3>
        </defaultStyle>
      </self>
    </children>
  </children>
  <children>
    <self itemName="Arrow L">
      <transform alignment="Left" arrayAxisOrder="XYZ">
        <offsetPosition x="4.02" y="-0.58" z="0" />
        <offsetRotation x="-0" y="0" z="0" />
        <scale x="0.8" y="0.8" z="1" />
        <mustDraw>1</mustDraw>
        <instanceCount>-1</instanceCount>
        <arrayInstances x="1" y="1" z="1" />
        <arraySpacing x="0" y="0" z="0" />
      </transform>
      <imageMesh atlas="MaestroGermanSigns:Ger Arrows">
        <mesh></mesh>
        <image>Black Forward medium</image>
      </imageMesh>
      <defaultStyle>
        <color>FFFFFFFF</color>
        <emissiveColor>FFFFFFFF</emissiveColor>
        <metallic>0</metallic>
        <smoothness>0</smoothness>
        <emissiveIntensity>0</emissiveIntensity>
        <emissiveExposureWeight>0</emissiveExposureWeight>
        <coatStrength>0</coatStrength>
        <colorMask1>FFFFFF</colorMask1>
        <colorMask2>FFFFFF</colorMask2>
        <colorMask3>FFFFFF</colorMask3>
      </defaultStyle>
    </self>
    <children>
      <self itemName="Arrow M">
        <transform alignment="Left" arrayAxisOrder="XYZ">
          <offsetPosition x="-2.25" y="-0.219999984" z="0" />
          <offsetRotation x="-0" y="0" z="0" />
          <scale x="0.4" y="0.4" z="1" />
          <mustDraw>1</mustDraw>
          <instanceCount>-1</instanceCount>
          <arrayInstances x="1" y="1" z="1" />
          <arraySpacing x="0" y="0" z="0" />
        </transform>
        <imageMesh atlas="MaestroGermanSigns:Ger Arrows">
          <mesh></mesh>
          <image>Black Motorway Small</image>
        </imageMesh>
        <defaultStyle>
          <color>FFFFFFFF</color>
          <emissiveColor>FFFFFFFF</emissiveColor>
          <metallic>0</metallic>
          <smoothness>0</smoothness>
          <emissiveIntensity>0</emissiveIntensity>
          <emissiveExposureWeight>0</emissiveExposureWeight>
          <coatStrength>0</coatStrength>
          <colorMask1>FFFFFF</colorMask1>
          <colorMask2>FFFFFF</colorMask2>
          <colorMask3>FFFFFF</colorMask3>
        </defaultStyle>
      </self>
    </children>
    <children>
      <self itemName="Arrow R">
        <transform alignment="Left" arrayAxisOrder="XYZ">
          <offsetPosition x="-4.7" y="0.06" z="0" />
          <offsetRotation x="-0" y="0" z="0" />
          <scale x="1" y="1" z="1" />
          <mustDraw>1</mustDraw>
          <instanceCount>-1</instanceCount>
          <arrayInstances x="1" y="1" z="1" />
          <arraySpacing x="0" y="0" z="0" />
        </transform>
        <imageMesh atlas="MaestroGermanSigns:Ger Arrows">
          <mesh></mesh>
          <image>Black with Exit Small</image>
        </imageMesh>
        <defaultStyle>
          <color>FFFFFFFF</color>
          <emissiveColor>FFFFFFFF</emissiveColor>
          <metallic>0</metallic>
          <smoothness>0</smoothness>
          <emissiveIntensity>0</emissiveIntensity>
          <emissiveExposureWeight>0</emissiveExposureWeight>
          <coatStrength>0</coatStrength>
          <colorMask1>FFFFFF</colorMask1>
          <colorMask2>FFFFFF</colorMask2>
          <colorMask3>FFFFFF</colorMask3>
        </defaultStyle>
      </self>
    </children>
  </children>
  <children>
    <self itemName="Backside">
      <transform alignment="Left" isAbsoluteScale="true" arrayAxisOrder="XYZ">
        <offsetPosition x="0" y="0" z="-0.075" />
        <offsetRotation x="-0" y="0" z="0" />
        <scale x="9" y="2.25" z="0.1" />
        <mustDraw>1</mustDraw>
        <instanceCount>-1</instanceCount>
        <arrayInstances x="1" y="1" z="1" />
        <arraySpacing x="0" y="0" z="0" />
      </transform>
      <whiteCubeMesh />
      <defaultStyle>
        <color>454545FF</color>
        <emissiveColor>FFFFFFFF</emissiveColor>
        <metallic>0</metallic>
        <smoothness>0</smoothness>
        <emissiveIntensity>0</emissiveIntensity>
        <emissiveExposureWeight>0</emissiveExposureWeight>
        <coatStrength>0</coatStrength>
        <colorMask1>FFFFFF</colorMask1>
        <colorMask2>FFFFFF</colorMask2>
        <colorMask3>FFFFFF</colorMask3>
      </defaultStyle>
    </self>
  </children>
</WELayout>